noctis_sdk/__init__.py
noctis_sdk/api_client.py
noctis_sdk/api_response.py
noctis_sdk/configuration.py
noctis_sdk/exceptions.py
noctis_sdk/rest.py
noctis_sdk/api/__init__.py
noctis_sdk/api/asns_api.py
noctis_sdk/api/dns_resolution_api.py
noctis_sdk/api/domains_api.py
noctis_sdk/api/file_operations_api.py
noctis_sdk/api/noctis_account_information_api.py
noctis_sdk/api/noctis_classic_lookup_reversing_api.py
noctis_sdk/api/noctis_classic_lookup_reversing_legacy_api.py
noctis_sdk/api/noctis_classic_monitors_api.py
noctis_sdk/api/noctis_feeds_api.py
noctis_sdk/api/noctis_vulpra_detect_api.py
noctis_sdk/api/noctis_vulpra_enrich_api.py
noctis_sdk/api/noctis_vulpra_investigate_api.py
noctis_sdk/api/scoring_algorithm_sr_api.py
noctis_sdk/api/visualize_api.py
noctis_sdk/models/__init__.py
noctis_sdk/models/account_data.py
noctis_sdk/models/account_info.py
noctis_sdk/models/account_information_response.py
noctis_sdk/models/brand_alert.py
noctis_sdk/models/brand_monitor_data.py
noctis_sdk/models/brand_monitor_response.py
noctis_sdk/models/contact_dto.py
noctis_sdk/models/contact_enrich_dto.py
noctis_sdk/models/contact_keys.py
noctis_sdk/models/domain_parsed_whois.py
noctis_sdk/models/domain_profile_data.py
noctis_sdk/models/domain_profile_response.py
noctis_sdk/models/domain_reputation_data.py
noctis_sdk/models/domain_reputation_response.py
noctis_sdk/models/domain_risk_dto.py
noctis_sdk/models/domain_risk_score_data.py
noctis_sdk/models/domain_risk_score_evidence_data.py
noctis_sdk/models/domain_risk_score_evidence_response.py
noctis_sdk/models/domain_risk_score_response.py
noctis_sdk/models/domain_whois_data.py
noctis_sdk/models/entity_types.py
noctis_sdk/models/escalation_info_dto.py
noctis_sdk/models/escalation_update_result_dto.py
noctis_sdk/models/feed_file_dto.py
noctis_sdk/models/feed_list_data.py
noctis_sdk/models/feed_list_response.py
noctis_sdk/models/generic_value_dto_integer.py
noctis_sdk/models/generic_value_dto_long.py
noctis_sdk-0.0.3.dist-info/METADATA
noctis_sdk-0.0.3.dist-info/WHEEL
noctis_sdk-0.0.3.dist-info/top_level.txt
noctis_sdk-0.0.3.dist-info/RECORD
