Metadata-Version: 2.4
Name: noctis-sdk
Version: 0.0.3
Summary: Python SDK for the NoctisNet API
Author-email: NoctisNet Team <support@noctisnet.com>
Project-URL: Homepage, https://github.com/NoctisNet/noctis-sdk-python
Project-URL: Bug Tracker, https://github.com/NoctisNet/noctis-sdk-python/issues
Classifier: Programming Language :: Python :: 3
Classifier: Operating System :: OS Independent
Requires-Python: >=3.9
Requires-Dist: urllib3<3.0.0,>=2.1.0
Requires-Dist: python-dateutil>=2.8.2
Requires-Dist: pydantic>=2
Requires-Dist: typing-extensions>=4.7.1
